{
  "packages/animal": {
    "root": [
      "packages/animal/package.json",
      "nx/core/package-json"
    ],
    "projectType": [
      "packages/animal/tsconfig.spec.json",
      "@nx/js/typescript"
    ],
    "targets": [
      "packages/animal/tsconfig.json",
      "@nx/js/typescript"
    ],
    "targets.typecheck": [
      "packages/animal/vite.config.ts",
      "@nx/vite/plugin"
    ],
    "targets.typecheck.dependsOn": [
      "packages/animal/vite.config.ts",
      "@nx/vite/plugin"
    ],
    "targets.typecheck.options": [
      "packages/animal/vite.config.ts",
      "@nx/vite/plugin"
    ],
    "targets.typecheck.cache": [
      "packages/animal/vite.config.ts",
      "@nx/vite/plugin"
    ],
    "targets.typecheck.inputs": [
      "packages/animal/vite.config.ts",
      "@nx/vite/plugin"
    ],
    "targets.typecheck.outputs": [
      "packages/animal/tsconfig.json",
      "@nx/js/typescript"
    ],
    "targets.typecheck.syncGenerators": [
      "packages/animal/vite.config.ts",
      "@nx/vite/plugin"
    ],
    "targets.typecheck.metadata": [
      "packages/animal/vite.config.ts",
      "@nx/vite/plugin"
    ],
    "targets.typecheck.executor": [
      "packages/animal/vite.config.ts",
      "@nx/vite/plugin"
    ],
    "targets.typecheck.options.cwd": [
      "packages/animal/vite.config.ts",
      "@nx/vite/plugin"
    ],
    "targets.typecheck.options.command": [
      "packages/animal/vite.config.ts",
      "@nx/vite/plugin"
    ],
    "targets.typecheck.metadata.technologies": [
      "packages/animal/tsconfig.json",
      "@nx/js/typescript"
    ],
    "targets.typecheck.metadata.technologies.0": [
      "packages/animal/tsconfig.json",
      "@nx/js/typescript"
    ],
    "targets.typecheck.metadata.description": [
      "packages/animal/vite.config.ts",
      "@nx/vite/plugin"
    ],
    "targets.typecheck.metadata.help": [
      "packages/animal/vite.config.ts",
      "@nx/vite/plugin"
    ],
    "targets.typecheck.metadata.help.command": [
      "packages/animal/tsconfig.json",
      "@nx/js/typescript"
    ],
    "targets.typecheck.metadata.help.example": [
      "packages/animal/tsconfig.json",
      "@nx/js/typescript"
    ],
    "targets.build": [
      "packages/animal/tsconfig.lib.json",
      "@nx/js/typescript"
    ],
    "targets.build.dependsOn": [
      "packages/animal/tsconfig.lib.json",
      "@nx/js/typescript"
    ],
    "targets.build.options": [
      "packages/animal/tsconfig.lib.json",
      "@nx/js/typescript"
    ],
    "targets.build.cache": [
      "packages/animal/tsconfig.lib.json",
      "@nx/js/typescript"
    ],
    "targets.build.inputs": [
      "packages/animal/tsconfig.lib.json",
      "@nx/js/typescript"
    ],
    "targets.build.outputs": [
      "packages/animal/tsconfig.lib.json",
      "@nx/js/typescript"
    ],
    "targets.build.syncGenerators": [
      "packages/animal/tsconfig.lib.json",
      "@nx/js/typescript"
    ],
    "targets.build.metadata": [
      "packages/animal/tsconfig.lib.json",
      "@nx/js/typescript"
    ],
    "targets.build.executor": [
      "packages/animal/tsconfig.lib.json",
      "@nx/js/typescript"
    ],
    "targets.build.options.cwd": [
      "packages/animal/tsconfig.lib.json",
      "@nx/js/typescript"
    ],
    "targets.build.options.command": [
      "packages/animal/tsconfig.lib.json",
      "@nx/js/typescript"
    ],
    "targets.build.metadata.technologies": [
      "packages/animal/tsconfig.lib.json",
      "@nx/js/typescript"
    ],
    "targets.build.metadata.technologies.0": [
      "packages/animal/tsconfig.lib.json",
      "@nx/js/typescript"
    ],
    "targets.build.metadata.description": [
      "packages/animal/tsconfig.lib.json",
      "@nx/js/typescript"
    ],
    "targets.build.metadata.help": [
      "packages/animal/tsconfig.lib.json",
      "@nx/js/typescript"
    ],
    "targets.build.metadata.help.command": [
      "packages/animal/tsconfig.lib.json",
      "@nx/js/typescript"
    ],
    "targets.build.metadata.help.example": [
      "packages/animal/tsconfig.lib.json",
      "@nx/js/typescript"
    ],
    "targets.build-deps": [
      "packages/animal/vite.config.ts",
      "@nx/vite/plugin"
    ],
    "targets.build-deps.dependsOn": [
      "packages/animal/vite.config.ts",
      "@nx/vite/plugin"
    ],
    "targets.watch-deps": [
      "packages/animal/vite.config.ts",
      "@nx/vite/plugin"
    ],
    "targets.watch-deps.continuous": [
      "packages/animal/vite.config.ts",
      "@nx/vite/plugin"
    ],
    "targets.watch-deps.dependsOn": [
      "packages/animal/vite.config.ts",
      "@nx/vite/plugin"
    ],
    "targets.watch-deps.executor": [
      "packages/animal/vite.config.ts",
      "@nx/vite/plugin"
    ],
    "targets.watch-deps.options": [
      "packages/animal/vite.config.ts",
      "@nx/vite/plugin"
    ],
    "targets.watch-deps.options.command": [
      "packages/animal/vite.config.ts",
      "@nx/vite/plugin"
    ],
    "targets.test": [
      "packages/animal/vite.config.ts",
      "@nx/vite/plugin"
    ],
    "targets.test.options": [
      "packages/animal/vite.config.ts",
      "@nx/vite/plugin"
    ],
    "targets.test.cache": [
      "packages/animal/vite.config.ts",
      "@nx/vite/plugin"
    ],
    "targets.test.inputs": [
      "packages/animal/vite.config.ts",
      "@nx/vite/plugin"
    ],
    "targets.test.outputs": [
      "packages/animal/vite.config.ts",
      "@nx/vite/plugin"
    ],
    "targets.test.metadata": [
      "packages/animal/vite.config.ts",
      "@nx/vite/plugin"
    ],
    "targets.test.executor": [
      "packages/animal/vite.config.ts",
      "@nx/vite/plugin"
    ],
    "targets.test.options.cwd": [
      "packages/animal/vite.config.ts",
      "@nx/vite/plugin"
    ],
    "targets.test.options.command": [
      "packages/animal/vite.config.ts",
      "@nx/vite/plugin"
    ],
    "targets.test.metadata.technologies": [
      "packages/animal/vite.config.ts",
      "@nx/vite/plugin"
    ],
    "targets.test.metadata.technologies.0": [
      "packages/animal/vite.config.ts",
      "@nx/vite/plugin"
    ],
    "targets.test.metadata.description": [
      "packages/animal/vite.config.ts",
      "@nx/vite/plugin"
    ],
    "targets.test.metadata.help": [
      "packages/animal/vite.config.ts",
      "@nx/vite/plugin"
    ],
    "targets.test.metadata.help.command": [
      "packages/animal/vite.config.ts",
      "@nx/vite/plugin"
    ],
    "targets.test.metadata.help.example": [
      "packages/animal/vite.config.ts",
      "@nx/vite/plugin"
    ],
    "targets.typecheck.metadata.technologies.1": [
      "packages/animal/vite.config.ts",
      "@nx/vite/plugin"
    ],
    "name": [
      "packages/animal/package.json",
      "nx/core/package-json"
    ],
    "tags": [
      "packages/animal/package.json",
      "nx/core/package-json"
    ],
    "tags.npm:private": [
      "packages/animal/package.json",
      "nx/core/package-json"
    ],
    "metadata.targetGroups": [
      "packages/animal/package.json",
      "nx/core/package-json"
    ],
    "metadata.js": [
      "packages/animal/package.json",
      "nx/core/package-json"
    ],
    "metadata.js.packageName": [
      "packages/animal/package.json",
      "nx/core/package-json"
    ],
    "metadata.js.packageExports": [
      "packages/animal/package.json",
      "nx/core/package-json"
    ],
    "metadata.js.packageMain": [
      "packages/animal/package.json",
      "nx/core/package-json"
    ],
    "metadata.js.isInPackageManagerWorkspaces": [
      "packages/animal/package.json",
      "nx/core/package-json"
    ],
    "targets.test.dependsOn": [
      "nx.json",
      "nx/target-defaults"
    ],
    "targets.test.parallelism": [
      "nx.json",
      "nx/target-defaults"
    ]
  },
  "packages/zoo": {
    "root": [
      "packages/zoo/package.json",
      "nx/core/package-json"
    ],
    "projectType": [
      "packages/zoo/tsconfig.spec.json",
      "@nx/js/typescript"
    ],
    "targets": [
      "packages/zoo/tsconfig.json",
      "@nx/js/typescript"
    ],
    "targets.typecheck": [
      "packages/zoo/vite.config.ts",
      "@nx/vite/plugin"
    ],
    "targets.typecheck.dependsOn": [
      "packages/zoo/vite.config.ts",
      "@nx/vite/plugin"
    ],
    "targets.typecheck.options": [
      "packages/zoo/vite.config.ts",
      "@nx/vite/plugin"
    ],
    "targets.typecheck.cache": [
      "packages/zoo/vite.config.ts",
      "@nx/vite/plugin"
    ],
    "targets.typecheck.inputs": [
      "packages/zoo/vite.config.ts",
      "@nx/vite/plugin"
    ],
    "targets.typecheck.outputs": [
      "packages/zoo/tsconfig.json",
      "@nx/js/typescript"
    ],
    "targets.typecheck.syncGenerators": [
      "packages/zoo/vite.config.ts",
      "@nx/vite/plugin"
    ],
    "targets.typecheck.metadata": [
      "packages/zoo/vite.config.ts",
      "@nx/vite/plugin"
    ],
    "targets.typecheck.executor": [
      "packages/zoo/vite.config.ts",
      "@nx/vite/plugin"
    ],
    "targets.typecheck.options.cwd": [
      "packages/zoo/vite.config.ts",
      "@nx/vite/plugin"
    ],
    "targets.typecheck.options.command": [
      "packages/zoo/vite.config.ts",
      "@nx/vite/plugin"
    ],
    "targets.typecheck.metadata.technologies": [
      "packages/zoo/tsconfig.json",
      "@nx/js/typescript"
    ],
    "targets.typecheck.metadata.technologies.0": [
      "packages/zoo/tsconfig.json",
      "@nx/js/typescript"
    ],
    "targets.typecheck.metadata.description": [
      "packages/zoo/vite.config.ts",
      "@nx/vite/plugin"
    ],
    "targets.typecheck.metadata.help": [
      "packages/zoo/vite.config.ts",
      "@nx/vite/plugin"
    ],
    "targets.typecheck.metadata.help.command": [
      "packages/zoo/tsconfig.json",
      "@nx/js/typescript"
    ],
    "targets.typecheck.metadata.help.example": [
      "packages/zoo/tsconfig.json",
      "@nx/js/typescript"
    ],
    "targets.build": [
      "packages/zoo/tsconfig.lib.json",
      "@nx/js/typescript"
    ],
    "targets.build.dependsOn": [
      "packages/zoo/tsconfig.lib.json",
      "@nx/js/typescript"
    ],
    "targets.build.options": [
      "packages/zoo/tsconfig.lib.json",
      "@nx/js/typescript"
    ],
    "targets.build.cache": [
      "packages/zoo/tsconfig.lib.json",
      "@nx/js/typescript"
    ],
    "targets.build.inputs": [
      "packages/zoo/tsconfig.lib.json",
      "@nx/js/typescript"
    ],
    "targets.build.outputs": [
      "packages/zoo/tsconfig.lib.json",
      "@nx/js/typescript"
    ],
    "targets.build.syncGenerators": [
      "packages/zoo/tsconfig.lib.json",
      "@nx/js/typescript"
    ],
    "targets.build.metadata": [
      "packages/zoo/tsconfig.lib.json",
      "@nx/js/typescript"
    ],
    "targets.build.executor": [
      "packages/zoo/tsconfig.lib.json",
      "@nx/js/typescript"
    ],
    "targets.build.options.cwd": [
      "packages/zoo/tsconfig.lib.json",
      "@nx/js/typescript"
    ],
    "targets.build.options.command": [
      "packages/zoo/tsconfig.lib.json",
      "@nx/js/typescript"
    ],
    "targets.build.metadata.technologies": [
      "packages/zoo/tsconfig.lib.json",
      "@nx/js/typescript"
    ],
    "targets.build.metadata.technologies.0": [
      "packages/zoo/tsconfig.lib.json",
      "@nx/js/typescript"
    ],
    "targets.build.metadata.description": [
      "packages/zoo/tsconfig.lib.json",
      "@nx/js/typescript"
    ],
    "targets.build.metadata.help": [
      "packages/zoo/tsconfig.lib.json",
      "@nx/js/typescript"
    ],
    "targets.build.metadata.help.command": [
      "packages/zoo/tsconfig.lib.json",
      "@nx/js/typescript"
    ],
    "targets.build.metadata.help.example": [
      "packages/zoo/tsconfig.lib.json",
      "@nx/js/typescript"
    ],
    "targets.build-deps": [
      "packages/zoo/vite.config.ts",
      "@nx/vite/plugin"
    ],
    "targets.build-deps.dependsOn": [
      "packages/zoo/vite.config.ts",
      "@nx/vite/plugin"
    ],
    "targets.watch-deps": [
      "packages/zoo/vite.config.ts",
      "@nx/vite/plugin"
    ],
    "targets.watch-deps.continuous": [
      "packages/zoo/vite.config.ts",
      "@nx/vite/plugin"
    ],
    "targets.watch-deps.dependsOn": [
      "packages/zoo/vite.config.ts",
      "@nx/vite/plugin"
    ],
    "targets.watch-deps.executor": [
      "packages/zoo/vite.config.ts",
      "@nx/vite/plugin"
    ],
    "targets.watch-deps.options": [
      "packages/zoo/vite.config.ts",
      "@nx/vite/plugin"
    ],
    "targets.watch-deps.options.command": [
      "packages/zoo/vite.config.ts",
      "@nx/vite/plugin"
    ],
    "targets.test": [
      "packages/zoo/vite.config.ts",
      "@nx/vite/plugin"
    ],
    "targets.test.options": [
      "packages/zoo/vite.config.ts",
      "@nx/vite/plugin"
    ],
    "targets.test.cache": [
      "packages/zoo/vite.config.ts",
      "@nx/vite/plugin"
    ],
    "targets.test.inputs": [
      "packages/zoo/vite.config.ts",
      "@nx/vite/plugin"
    ],
    "targets.test.outputs": [
      "packages/zoo/vite.config.ts",
      "@nx/vite/plugin"
    ],
    "targets.test.metadata": [
      "packages/zoo/vite.config.ts",
      "@nx/vite/plugin"
    ],
    "targets.test.executor": [
      "packages/zoo/vite.config.ts",
      "@nx/vite/plugin"
    ],
    "targets.test.options.cwd": [
      "packages/zoo/vite.config.ts",
      "@nx/vite/plugin"
    ],
    "targets.test.options.command": [
      "packages/zoo/vite.config.ts",
      "@nx/vite/plugin"
    ],
    "targets.test.metadata.technologies": [
      "packages/zoo/vite.config.ts",
      "@nx/vite/plugin"
    ],
    "targets.test.metadata.technologies.0": [
      "packages/zoo/vite.config.ts",
      "@nx/vite/plugin"
    ],
    "targets.test.metadata.description": [
      "packages/zoo/vite.config.ts",
      "@nx/vite/plugin"
    ],
    "targets.test.metadata.help": [
      "packages/zoo/vite.config.ts",
      "@nx/vite/plugin"
    ],
    "targets.test.metadata.help.command": [
      "packages/zoo/vite.config.ts",
      "@nx/vite/plugin"
    ],
    "targets.test.metadata.help.example": [
      "packages/zoo/vite.config.ts",
      "@nx/vite/plugin"
    ],
    "targets.typecheck.metadata.technologies.1": [
      "packages/zoo/vite.config.ts",
      "@nx/vite/plugin"
    ],
    "name": [
      "packages/zoo/package.json",
      "nx/core/package-json"
    ],
    "tags": [
      "packages/zoo/package.json",
      "nx/core/package-json"
    ],
    "tags.npm:private": [
      "packages/zoo/package.json",
      "nx/core/package-json"
    ],
    "metadata.targetGroups": [
      "packages/zoo/package.json",
      "nx/core/package-json"
    ],
    "metadata.js": [
      "packages/zoo/package.json",
      "nx/core/package-json"
    ],
    "metadata.js.packageName": [
      "packages/zoo/package.json",
      "nx/core/package-json"
    ],
    "metadata.js.packageExports": [
      "packages/zoo/package.json",
      "nx/core/package-json"
    ],
    "metadata.js.packageMain": [
      "packages/zoo/package.json",
      "nx/core/package-json"
    ],
    "metadata.js.isInPackageManagerWorkspaces": [
      "packages/zoo/package.json",
      "nx/core/package-json"
    ],
    "targets.test.dependsOn": [
      "nx.json",
      "nx/target-defaults"
    ],
    "targets.test.parallelism": [
      "nx.json",
      "nx/target-defaults"
    ]
  }
}